fluidattacks_core/__init__.py
fluidattacks_core/py.typed
fluidattacks_core/aio/__init__.py
fluidattacks_core/aio/processes.py
fluidattacks_core/aio/runners.py
fluidattacks_core/aio/tasks.py
fluidattacks_core/aio/threads.py
fluidattacks_core/authz/__init__.py
fluidattacks_core/authz/py.typed
fluidattacks_core/authz/types.py
fluidattacks_core/cpg/__init__.py
fluidattacks_core/cpg/joern.py
fluidattacks_core/filesystem/__init__.py
fluidattacks_core/filesystem/defaults.py
fluidattacks_core/git/__init__.py
fluidattacks_core/git/classes.py
fluidattacks_core/git/clone.py
fluidattacks_core/git/codecommit_utils.py
fluidattacks_core/git/constants.py
fluidattacks_core/git/delete_files.py
fluidattacks_core/git/download_file.py
fluidattacks_core/git/download_repo.py
fluidattacks_core/git/https_utils.py
fluidattacks_core/git/py.typed
fluidattacks_core/git/remote.py
fluidattacks_core/git/ssh_utils.py
fluidattacks_core/git/utils.py
fluidattacks_core/git/warp.py
fluidattacks_core/http/__init__.py
fluidattacks_core/http/client.py
fluidattacks_core/http/validations.py
fluidattacks_core/logging/__init__.py
fluidattacks_core/logging/filters.py
fluidattacks_core/logging/formatters.py
fluidattacks_core/logging/handlers.py
fluidattacks_core/logging/presets.py
fluidattacks_core/logging/utils.py
fluidattacks_core/logging/sources/__init__.py
fluidattacks_core/logging/sources/types.py
fluidattacks_core/logging/sources/utils.py
fluidattacks_core/sarif/__init__.py
fluidattacks_core/semver/__init__.py
fluidattacks_core/semver/match_versions.py
fluidattacks_core/serializers/__init__.py
fluidattacks_core/serializers/snippet.py
fluidattacks_core/serializers/syntax.py
fluidattacks_core-5.1.0.dist-info/METADATA
fluidattacks_core-5.1.0.dist-info/WHEEL
fluidattacks_core-5.1.0.dist-info/top_level.txt
fluidattacks_core-5.1.0.dist-info/RECORD
