Metadata-Version: 2.4
Name: fluidattacks-core
Version: 5.1.0
Summary: Fluid Attacks Core Library
Author-email: Development <development@fluidattacks.com>
License: MPL-2.0
Classifier: Development Status :: 1 - Planning
Classifier: Intended Audience :: Developers
Classifier: License :: OSI Approved :: Mozilla Public License 2.0 (MPL 2.0)
Classifier: Programming Language :: Python :: 3
Classifier: Programming Language :: Python :: 3.11
Classifier: Topic :: Software Development :: Libraries
Requires-Python: >=3.11
Provides-Extra: aio
Requires-Dist: uvloop>=0.21.0; extra == "aio"
Provides-Extra: authz
Provides-Extra: git
Requires-Dist: aiohttp>=3.10.0; extra == "git"
Requires-Dist: aiofiles>=23.2.1; extra == "git"
Requires-Dist: boto3>=1.34; extra == "git"
Requires-Dist: botocore>=1.40.18; extra == "git"
Requires-Dist: GitPython>=3.1.41; extra == "git"
Requires-Dist: pathspec>=0.12.1; extra == "git"
Requires-Dist: urllib3>=2.6.1; extra == "git"
Provides-Extra: http
Requires-Dist: aiohttp>=3.10.0; extra == "http"
Requires-Dist: certifi>=2024.8.30; extra == "http"
Requires-Dist: urllib3>=2.6.1; extra == "http"
Provides-Extra: logging
Requires-Dist: simplejson>=3.20.1; extra == "logging"
Requires-Dist: python-json-logger>=3.3.0; extra == "logging"
Provides-Extra: serializers
Requires-Dist: more-itertools>=10.0.0; extra == "serializers"
Requires-Dist: tree-sitter-c-sharp>=0.23.1; extra == "serializers"
Requires-Dist: tree-sitter-go>=0.23.4; extra == "serializers"
Requires-Dist: tree-sitter-html>=0.23.2; extra == "serializers"
Requires-Dist: tree-sitter-java>=0.23.4; extra == "serializers"
Requires-Dist: tree-sitter-javascript>=0.23.1; extra == "serializers"
Requires-Dist: tree-sitter-json>=0.24.8; extra == "serializers"
Requires-Dist: tree-sitter-kotlin>=1.0.1; extra == "serializers"
Requires-Dist: tree-sitter-php==0.23.11; extra == "serializers"
Requires-Dist: tree-sitter-python>=0.23.4; extra == "serializers"
Requires-Dist: tree-sitter-typescript>=0.23.2; extra == "serializers"
Requires-Dist: tree-sitter-xml>=0.7.0; extra == "serializers"
Requires-Dist: tree-sitter-yaml>=0.7.0; extra == "serializers"
Requires-Dist: tree-sitter>=0.25.2; extra == "serializers"
Requires-Dist: tree-sitter-dart-orchard==0.3.2; extra == "serializers"
Provides-Extra: cpg
Requires-Dist: aioboto3>=13.3.0; extra == "cpg"
Requires-Dist: platformdirs>=4.3.8; extra == "cpg"
Provides-Extra: filesystem
Provides-Extra: sarif
Requires-Dist: pydantic>=2.12.3; extra == "sarif"
Provides-Extra: semver
Provides-Extra: all
Requires-Dist: fluidattacks-core[aio]; extra == "all"
Requires-Dist: fluidattacks-core[authz]; extra == "all"
Requires-Dist: fluidattacks-core[cpg]; extra == "all"
Requires-Dist: fluidattacks-core[filesystem]; extra == "all"
Requires-Dist: fluidattacks-core[git]; extra == "all"
Requires-Dist: fluidattacks-core[http]; extra == "all"
Requires-Dist: fluidattacks-core[logging]; extra == "all"
Requires-Dist: fluidattacks-core[sarif]; extra == "all"
Requires-Dist: fluidattacks-core[semver]; extra == "all"
Requires-Dist: fluidattacks-core[serializers]; extra == "all"
